cksync/__init__.py
cksync/_type_utils.py
cksync/check.py
cksync/cli/__init__.py
cksync/cli/main.py
cksync/cli/parser.py
cksync/cli/result.py
cksync/pyproject/__init__.py
cksync/pyproject/pyproject_toml.py
cksync/pyproject/lockfiles/__init__.py
cksync/pyproject/lockfiles/_base.py
cksync/pyproject/lockfiles/poetry_lock.py
cksync/pyproject/lockfiles/uv_lock.py
cksync-0.1.3.dist-info/METADATA
cksync-0.1.3.dist-info/WHEEL
cksync-0.1.3.dist-info/entry_points.txt
cksync-0.1.3.dist-info/licenses/LICENSE
cksync-0.1.3.dist-info/RECORD
