Metadata-Version: 2.4
Name: cksync
Version: 0.1.3
Summary: cksync before you change dependency mgmt tools!
Author-email: Nick Grisafi <njgrisafi@gmail.com>
License-File: LICENSE
Classifier: Intended Audience :: Developers
Classifier: License :: OSI Approved :: MIT License
Classifier: Programming Language :: Python :: 3 :: Only
Classifier: Programming Language :: Python :: 3.11
Classifier: Programming Language :: Python :: 3.12
Classifier: Programming Language :: Python :: 3.13
Classifier: Typing :: Typed
Requires-Python: >=3.11
Requires-Dist: rich>=13.0.0
